datapackage_pipelines_ckan/VERSION
datapackage_pipelines_ckan/__init__.py
datapackage_pipelines_ckan/utils.py
datapackage_pipelines_ckan/processors/__init__.py
datapackage_pipelines_ckan/processors/add_ckan_resource.py
datapackage_pipelines_ckan/processors/dump/__init__.py
datapackage_pipelines_ckan/processors/dump/to_ckan.py
datapackage_pipelines_ckan-0.0.2b0.dist-info/DESCRIPTION.rst
datapackage_pipelines_ckan-0.0.2b0.dist-info/METADATA
datapackage_pipelines_ckan-0.0.2b0.dist-info/RECORD
datapackage_pipelines_ckan-0.0.2b0.dist-info/WHEEL
datapackage_pipelines_ckan-0.0.2b0.dist-info/metadata.json
datapackage_pipelines_ckan-0.0.2b0.dist-info/top_level.txt
