Metadata-Version: 2.0
Name: datapackage-pipelines-ckan
Version: 0.0.2b0
Summary: {{ DESCRIPTION }}
Home-page: https://github.com/frictionlessdata/datapackage-pipelines-ckan
Author: Open Knowledge International
Author-email: info@okfn.org
License: MIT
Keywords: data,ckan
Platform: UNKNOWN
Classifier: Development Status :: 4 - Beta
Classifier: Environment :: Web Environment
Classifier: Intended Audience :: Developers
Classifier: License :: OSI Approved :: MIT License
Classifier: Operating System :: OS Independent
Classifier: Programming Language :: Python :: 3.6
Classifier: Topic :: Internet :: WWW/HTTP :: Dynamic Content
Classifier: Topic :: Software Development :: Libraries :: Python Modules
Requires-Dist: datapackage-pipelines (<2.0,>=1.0)
Requires-Dist: ckan-datapackage-tools
Requires-Dist: tableschema-ckan-datastore
Provides-Extra: develop
Requires-Dist: pylama; extra == 'develop'
Requires-Dist: tox; extra == 'develop'
Requires-Dist: mock; extra == 'develop'
Requires-Dist: requests-mock; extra == 'develop'
